[
  {
    "_links": {
      "ancestors": {
        "href": "<base>/api/ontologies/gitissue502/terms/http%253A%252F%252Fpurl.obolibrary.org%252Fobo%252FCL_0000548/ancestors"
      },
      "children": {
        "href": "<base>/api/ontologies/gitissue502/terms/http%253A%252F%252Fpurl.obolibrary.org%252Fobo%252FCL_0000548/children"
      },
      "descendants": {
        "href": "<base>/api/ontologies/gitissue502/terms/http%253A%252F%252Fpurl.obolibrary.org%252Fobo%252FCL_0000548/descendants"
      },
      "graph": {
        "href": "<base>/api/ontologies/gitissue502/terms/http%253A%252F%252Fpurl.obolibrary.org%252Fobo%252FCL_0000548/graph"
      },
      "hierarchicalAncestors": {
        "href": "<base>/api/ontologies/gitissue502/terms/http%253A%252F%252Fpurl.obolibrary.org%252Fobo%252FCL_0000548/hierarchicalAncestors"
      },
      "hierarchicalChildren": {
        "href": "<base>/api/ontologies/gitissue502/terms/http%253A%252F%252Fpurl.obolibrary.org%252Fobo%252FCL_0000548/hierarchicalChildren"
      },
      "hierarchicalDescendants": {
        "href": "<base>/api/ontologies/gitissue502/terms/http%253A%252F%252Fpurl.obolibrary.org%252Fobo%252FCL_0000548/hierarchicalDescendants"
      },
      "hierarchicalParents": {
        "href": "<base>/api/ontologies/gitissue502/terms/http%253A%252F%252Fpurl.obolibrary.org%252Fobo%252FCL_0000548/hierarchicalParents"
      },
      "jstree": {
        "href": "<base>/api/ontologies/gitissue502/terms/http%253A%252F%252Fpurl.obolibrary.org%252Fobo%252FCL_0000548/jstree"
      },
      "only_in_taxon": {
        "href": "<base>/api/ontologies/gitissue502/terms/http%253A%252F%252Fpurl.obolibrary.org%252Fobo%252FCL_0000548/http%253A%252F%252Fpurl.obolibrary.org%252Fobo%252FRO_0002160"
      },
      "parents": {
        "href": "<base>/api/ontologies/gitissue502/terms/http%253A%252F%252Fpurl.obolibrary.org%252Fobo%252FCL_0000548/parents"
      },
      "self": {
        "href": "<base>/api/ontologies/gitissue502/terms/http%253A%252F%252Fpurl.obolibrary.org%252Fobo%252FCL_0000548?lang=en"
      }
    },
    "annotation": {},
    "description": [
      "A native cell that is part of some Metazoa."
    ],
    "has_children": true,
    "iri": "http://purl.obolibrary.org/obo/CL_0000548",
    "is_defining_ontology": false,
    "is_obsolete": false,
    "is_preferred_root": false,
    "is_root": false,
    "label": "animal cell",
    "lang": "en",
    "obo_id": "CL:0000548",
    "ontology_iri": "http://purl.obolibrary.org/obo/mondo.owl",
    "ontology_name": "gitissue502",
    "ontology_prefix": "gitIssue502",
    "short_form": "CL_0000548",
    "synonyms": []
  }
]