[
  {
    "_links": {
      "ancestors": {
        "href": "<base>/api/ontologies/owl/terms/http%253A%252F%252Fwww.w3.org%252F2002%252F07%252Fowl%2523Restriction/ancestors"
      },
      "graph": {
        "href": "<base>/api/ontologies/owl/terms/http%253A%252F%252Fwww.w3.org%252F2002%252F07%252Fowl%2523Restriction/graph"
      },
      "hierarchicalAncestors": {
        "href": "<base>/api/ontologies/owl/terms/http%253A%252F%252Fwww.w3.org%252F2002%252F07%252Fowl%2523Restriction/hierarchicalAncestors"
      },
      "hierarchicalParents": {
        "href": "<base>/api/ontologies/owl/terms/http%253A%252F%252Fwww.w3.org%252F2002%252F07%252Fowl%2523Restriction/hierarchicalParents"
      },
      "jstree": {
        "href": "<base>/api/ontologies/owl/terms/http%253A%252F%252Fwww.w3.org%252F2002%252F07%252Fowl%2523Restriction/jstree"
      },
      "parents": {
        "href": "<base>/api/ontologies/owl/terms/http%253A%252F%252Fwww.w3.org%252F2002%252F07%252Fowl%2523Restriction/parents"
      },
      "self": {
        "href": "<base>/api/ontologies/owl/terms/http%253A%252F%252Fwww.w3.org%252F2002%252F07%252Fowl%2523Restriction?lang=en"
      }
    },
    "annotation": {},
    "description": [
      "The class of property restrictions."
    ],
    "has_children": false,
    "iri": "http://www.w3.org/2002/07/owl#Restriction",
    "is_defining_ontology": true,
    "is_obsolete": false,
    "is_preferred_root": false,
    "is_root": false,
    "label": "Restriction",
    "lang": "en",
    "obo_id": "OWL:Restriction",
    "ontology_iri": "http://www.w3.org/2002/07/owl",
    "ontology_name": "owl",
    "short_form": "OWL_Restriction",
    "synonyms": []
  }
]