{
  "iri": "http://purl.obolibrary.org/obo/IAO_0000582",
  "lang": "en",
  "description": [],
  "synonyms": [],
  "annotation": {
    "has curation status": [
      "http://purl.obolibrary.org/obo/IAO_0000123"
    ]
  },
  "label": "time stamped measurement datum",
  "ontology_name": "duo",
  "ontology_prefix": "DUO",
  "ontology_iri": "http://purl.obolibrary.org/obo/duo.owl",
  "is_obsolete": false,
  "is_defining_ontology": false,
  "has_children": false,
  "is_root": false,
  "short_form": "IAO_0000582",
  "obo_id": "IAO:0000582",
  "is_preferred_root": false,
  "_links": {
    "self": {
      "href": "http://localhost:8080/api/ontologies/duo/terms/http%253A%252F%252Fpurl.obolibrary.org%252Fobo%252FIAO_0000582?lang=en"
    },
    "parents": {
      "href": "http://localhost:8080/api/ontologies/duo/terms/http%253A%252F%252Fpurl.obolibrary.org%252Fobo%252FIAO_0000582/parents"
    },
    "ancestors": {
      "href": "http://localhost:8080/api/ontologies/duo/terms/http%253A%252F%252Fpurl.obolibrary.org%252Fobo%252FIAO_0000582/ancestors"
    },
    "hierarchicalParents": {
      "href": "http://localhost:8080/api/ontologies/duo/terms/http%253A%252F%252Fpurl.obolibrary.org%252Fobo%252FIAO_0000582/hierarchicalParents"
    },
    "hierarchicalAncestors": {
      "href": "http://localhost:8080/api/ontologies/duo/terms/http%253A%252F%252Fpurl.obolibrary.org%252Fobo%252FIAO_0000582/hierarchicalAncestors"
    },
    "jstree": {
      "href": "http://localhost:8080/api/ontologies/duo/terms/http%253A%252F%252Fpurl.obolibrary.org%252Fobo%252FIAO_0000582/jstree"
    },
    "graph": {
      "href": "http://localhost:8080/api/ontologies/duo/terms/http%253A%252F%252Fpurl.obolibrary.org%252Fobo%252FIAO_0000582/graph"
    }
  }
}