[
  {
    "_links": {
      "ancestors": {
        "href": "<base>/api/ontologies/efo/terms/http%253A%252F%252Fpurl.obolibrary.org%252Fobo%252FUBERON_0000467/ancestors"
      },
      "graph": {
        "href": "<base>/api/ontologies/efo/terms/http%253A%252F%252Fpurl.obolibrary.org%252Fobo%252FUBERON_0000467/graph"
      },
      "hierarchicalAncestors": {
        "href": "<base>/api/ontologies/efo/terms/http%253A%252F%252Fpurl.obolibrary.org%252Fobo%252FUBERON_0000467/hierarchicalAncestors"
      },
      "hierarchicalParents": {
        "href": "<base>/api/ontologies/efo/terms/http%253A%252F%252Fpurl.obolibrary.org%252Fobo%252FUBERON_0000467/hierarchicalParents"
      },
      "jstree": {
        "href": "<base>/api/ontologies/efo/terms/http%253A%252F%252Fpurl.obolibrary.org%252Fobo%252FUBERON_0000467/jstree"
      },
      "parents": {
        "href": "<base>/api/ontologies/efo/terms/http%253A%252F%252Fpurl.obolibrary.org%252Fobo%252FUBERON_0000467/parents"
      },
      "self": {
        "href": "<base>/api/ontologies/efo/terms/http%253A%252F%252Fpurl.obolibrary.org%252Fobo%252FUBERON_0000467?lang=en"
      }
    },
    "annotation": {},
    "description": [],
    "has_children": false,
    "in_subset": [],
    "iri": "http://purl.obolibrary.org/obo/UBERON_0000467",
    "is_defining_ontology": true,
    "is_obsolete": false,
    "is_preferred_root": false,
    "is_root": false,
    "label": "anatomical system",
    "lang": "en",
    "obo_definition_citation": [],
    "obo_id": "UBERON:0000467",
    "obo_synonym": [],
    "obo_xref": [],
    "ontology_iri": "http://www.ebi.ac.uk/efo/efo.owl",
    "ontology_name": "efo",
    "ontology_prefix": "EFO",
    "short_form": "UBERON_0000467",
    "synonyms": []
  },
  {
    "_links": {
      "ancestors": {
        "href": "<base>/api/ontologies/efo/terms/http%253A%252F%252Fpurl.obolibrary.org%252Fobo%252FUBERON_0000483/ancestors"
      },
      "graph": {
        "href": "<base>/api/ontologies/efo/terms/http%253A%252F%252Fpurl.obolibrary.org%252Fobo%252FUBERON_0000483/graph"
      },
      "hierarchicalAncestors": {
        "href": "<base>/api/ontologies/efo/terms/http%253A%252F%252Fpurl.obolibrary.org%252Fobo%252FUBERON_0000483/hierarchicalAncestors"
      },
      "hierarchicalParents": {
        "href": "<base>/api/ontologies/efo/terms/http%253A%252F%252Fpurl.obolibrary.org%252Fobo%252FUBERON_0000483/hierarchicalParents"
      },
      "jstree": {
        "href": "<base>/api/ontologies/efo/terms/http%253A%252F%252Fpurl.obolibrary.org%252Fobo%252FUBERON_0000483/jstree"
      },
      "parents": {
        "href": "<base>/api/ontologies/efo/terms/http%253A%252F%252Fpurl.obolibrary.org%252Fobo%252FUBERON_0000483/parents"
      },
      "self": {
        "href": "<base>/api/ontologies/efo/terms/http%253A%252F%252Fpurl.obolibrary.org%252Fobo%252FUBERON_0000483?lang=en"
      }
    },
    "annotation": {},
    "description": [],
    "has_children": false,
    "in_subset": [],
    "iri": "http://purl.obolibrary.org/obo/UBERON_0000483",
    "is_defining_ontology": true,
    "is_obsolete": false,
    "is_preferred_root": false,
    "is_root": false,
    "label": "epithelium",
    "lang": "en",
    "obo_definition_citation": [],
    "obo_id": "UBERON:0000483",
    "obo_synonym": [],
    "obo_xref": [],
    "ontology_iri": "http://www.ebi.ac.uk/efo/efo.owl",
    "ontology_name": "efo",
    "ontology_prefix": "EFO",
    "short_form": "UBERON_0000483",
    "synonyms": []
  },
  {
    "_links": {
      "ancestors": {
        "href": "<base>/api/ontologies/efo/terms/http%253A%252F%252Fpurl.obolibrary.org%252Fobo%252FUBERON_0000916/ancestors"
      },
      "graph": {
        "href": "<base>/api/ontologies/efo/terms/http%253A%252F%252Fpurl.obolibrary.org%252Fobo%252FUBERON_0000916/graph"
      },
      "hierarchicalAncestors": {
        "href": "<base>/api/ontologies/efo/terms/http%253A%252F%252Fpurl.obolibrary.org%252Fobo%252FUBERON_0000916/hierarchicalAncestors"
      },
      "hierarchicalParents": {
        "href": "<base>/api/ontologies/efo/terms/http%253A%252F%252Fpurl.obolibrary.org%252Fobo%252FUBERON_0000916/hierarchicalParents"
      },
      "jstree": {
        "href": "<base>/api/ontologies/efo/terms/http%253A%252F%252Fpurl.obolibrary.org%252Fobo%252FUBERON_0000916/jstree"
      },
      "parents": {
        "href": "<base>/api/ontologies/efo/terms/http%253A%252F%252Fpurl.obolibrary.org%252Fobo%252FUBERON_0000916/parents"
      },
      "self": {
        "href": "<base>/api/ontologies/efo/terms/http%253A%252F%252Fpurl.obolibrary.org%252Fobo%252FUBERON_0000916?lang=en"
      }
    },
    "annotation": {},
    "description": [],
    "has_children": false,
    "in_subset": [],
    "iri": "http://purl.obolibrary.org/obo/UBERON_0000916",
    "is_defining_ontology": true,
    "is_obsolete": false,
    "is_preferred_root": false,
    "is_root": false,
    "label": "abdomen",
    "lang": "en",
    "obo_definition_citation": [],
    "obo_id": "UBERON:0000916",
    "obo_synonym": [],
    "obo_xref": [],
    "ontology_iri": "http://www.ebi.ac.uk/efo/efo.owl",
    "ontology_name": "efo",
    "ontology_prefix": "EFO",
    "short_form": "UBERON_0000916",
    "synonyms": []
  },
  {
    "_links": {
      "ancestors": {
        "href": "<base>/api/ontologies/efo/terms/http%253A%252F%252Fpurl.obolibrary.org%252Fobo%252FUBERON_0002100/ancestors"
      },
      "graph": {
        "href": "<base>/api/ontologies/efo/terms/http%253A%252F%252Fpurl.obolibrary.org%252Fobo%252FUBERON_0002100/graph"
      },
      "hierarchicalAncestors": {
        "href": "<base>/api/ontologies/efo/terms/http%253A%252F%252Fpurl.obolibrary.org%252Fobo%252FUBERON_0002100/hierarchicalAncestors"
      },
      "hierarchicalParents": {
        "href": "<base>/api/ontologies/efo/terms/http%253A%252F%252Fpurl.obolibrary.org%252Fobo%252FUBERON_0002100/hierarchicalParents"
      },
      "jstree": {
        "href": "<base>/api/ontologies/efo/terms/http%253A%252F%252Fpurl.obolibrary.org%252Fobo%252FUBERON_0002100/jstree"
      },
      "parents": {
        "href": "<base>/api/ontologies/efo/terms/http%253A%252F%252Fpurl.obolibrary.org%252Fobo%252FUBERON_0002100/parents"
      },
      "self": {
        "href": "<base>/api/ontologies/efo/terms/http%253A%252F%252Fpurl.obolibrary.org%252Fobo%252FUBERON_0002100?lang=en"
      }
    },
    "annotation": {},
    "description": [],
    "has_children": false,
    "in_subset": [],
    "iri": "http://purl.obolibrary.org/obo/UBERON_0002100",
    "is_defining_ontology": true,
    "is_obsolete": false,
    "is_preferred_root": false,
    "is_root": false,
    "label": "trunk",
    "lang": "en",
    "obo_definition_citation": [],
    "obo_id": "UBERON:0002100",
    "obo_synonym": [],
    "obo_xref": [],
    "ontology_iri": "http://www.ebi.ac.uk/efo/efo.owl",
    "ontology_name": "efo",
    "ontology_prefix": "EFO",
    "short_form": "UBERON_0002100",
    "synonyms": []
  },
  {
    "_links": {
      "ancestors": {
        "href": "<base>/api/ontologies/efo/terms/http%253A%252F%252Fpurl.obolibrary.org%252Fobo%252FUBERON_0013702/ancestors"
      },
      "graph": {
        "href": "<base>/api/ontologies/efo/terms/http%253A%252F%252Fpurl.obolibrary.org%252Fobo%252FUBERON_0013702/graph"
      },
      "hierarchicalAncestors": {
        "href": "<base>/api/ontologies/efo/terms/http%253A%252F%252Fpurl.obolibrary.org%252Fobo%252FUBERON_0013702/hierarchicalAncestors"
      },
      "hierarchicalParents": {
        "href": "<base>/api/ontologies/efo/terms/http%253A%252F%252Fpurl.obolibrary.org%252Fobo%252FUBERON_0013702/hierarchicalParents"
      },
      "jstree": {
        "href": "<base>/api/ontologies/efo/terms/http%253A%252F%252Fpurl.obolibrary.org%252Fobo%252FUBERON_0013702/jstree"
      },
      "parents": {
        "href": "<base>/api/ontologies/efo/terms/http%253A%252F%252Fpurl.obolibrary.org%252Fobo%252FUBERON_0013702/parents"
      },
      "self": {
        "href": "<base>/api/ontologies/efo/terms/http%253A%252F%252Fpurl.obolibrary.org%252Fobo%252FUBERON_0013702?lang=en"
      }
    },
    "annotation": {},
    "description": [],
    "has_children": false,
    "in_subset": [],
    "iri": "http://purl.obolibrary.org/obo/UBERON_0013702",
    "is_defining_ontology": true,
    "is_obsolete": false,
    "is_preferred_root": false,
    "is_root": false,
    "label": "body proper",
    "lang": "en",
    "obo_definition_citation": [],
    "obo_id": "UBERON:0013702",
    "obo_synonym": [],
    "obo_xref": [],
    "ontology_iri": "http://www.ebi.ac.uk/efo/efo.owl",
    "ontology_name": "efo",
    "ontology_prefix": "EFO",
    "short_form": "UBERON_0013702",
    "synonyms": []
  }
]