{
  "iri": "http://purl.obolibrary.org/obo/RO_0002490",
  "lang": "en",
  "description": [
    "x existence overlaps y if and only if either (a) the start of x is part of y or (b) the end of x is part of y. Formally: x existence starts and ends during y iff (α(x) >= α(y) & α(x) <= ω(y)) OR (ω(x) <= ω(y) & ω(x) >= α(y))"
  ],
  "synonyms": [],
  "annotation": {},
  "label": "existence overlaps",
  "ontology_name": "gitissue502",
  "ontology_prefix": "gitIssue502",
  "ontology_iri": "http://purl.obolibrary.org/obo/mondo.owl",
  "is_obsolete": false,
  "is_defining_ontology": false,
  "has_children": true,
  "is_root": false,
  "short_form": "RO_0002490",
  "obo_id": "RO:0002490",
  "_links": {
    "self": {
      "href": "http://localhost:8080/api/ontologies/gitissue502/properties/http%253A%252F%252Fpurl.obolibrary.org%252Fobo%252FRO_0002490?lang=en"
    },
    "parents": {
      "href": "http://localhost:8080/api/ontologies/gitissue502/properties/http%253A%252F%252Fpurl.obolibrary.org%252Fobo%252FRO_0002490/parents"
    },
    "ancestors": {
      "href": "http://localhost:8080/api/ontologies/gitissue502/properties/http%253A%252F%252Fpurl.obolibrary.org%252Fobo%252FRO_0002490/ancestors"
    },
    "jstree": {
      "href": "http://localhost:8080/api/ontologies/gitissue502/properties/http%253A%252F%252Fpurl.obolibrary.org%252Fobo%252FRO_0002490/jstree"
    },
    "children": {
      "href": "http://localhost:8080/api/ontologies/gitissue502/properties/http%253A%252F%252Fpurl.obolibrary.org%252Fobo%252FRO_0002490/children"
    },
    "descendants": {
      "href": "http://localhost:8080/api/ontologies/gitissue502/properties/http%253A%252F%252Fpurl.obolibrary.org%252Fobo%252FRO_0002490/descendants"
    }
  }
}